LICENSE
README.md
pyproject.toml
fade/__init__.py
fade/data.py
fade/default_config.yaml
fade/hooks.py
fade/llm.py
fade/pipeline.py
fade/results.py
fade/utils.py
fade/visualization.py
fade_language.egg-info/PKG-INFO
fade_language.egg-info/SOURCES.txt
fade_language.egg-info/dependency_links.txt
fade_language.egg-info/requires.txt
fade_language.egg-info/top_level.txt