Metadata-Version: 2.2
Name: fade-language
Version: 0.1.0
Summary: FADE: Why Bad Descriptions Happen to Good Features
Author: Bruno Puri, Aakriti Jain, Elena Golimblevskaia
License: BSD 3-clause
Project-URL: Homepage, https://github.com/brunibrun/FADE/
Project-URL: Bug Tracker, https://github.com/brunibrun/FADE/issues
Classifier: Programming Language :: Python :: 3
Classifier: License :: OSI Approved :: BSD License
Classifier: Operating System :: OS Independent
Classifier: Intended Audience :: Science/Research
Classifier: Topic :: Scientific/Engineering :: Artificial Intelligence
Requires-Python: >=3.7
License-File: LICENSE
Requires-Dist: torch>=2.3.0
Requires-Dist: transformers>=4.40.2
Requires-Dist: scikit-learn>=1.2.2
Requires-Dist: langchain>=0.2.5
Requires-Dist: langchain-community>=0.2.5
Requires-Dist: langchain_ollama==0.2.3
Requires-Dist: langchain-openai>=0.1.8
Requires-Dist: matplotlib>=3.7.2
Requires-Dist: seaborn>=0.12.2
Requires-Dist: numpy>=1.25.2
Requires-Dist: pandas>=2.2.2
Requires-Dist: h5py
Requires-Dist: pydantic
Requires-Dist: PyYAML
